<?xml version="1.0" encoding="UTF-8" standalone="no"?>
<Sportsmans>
<sportsman>
<Фамилия>Палюлин(-а)</Фамилия>
<Имя>Ника</Имя>
<Отчество>Валерьянович(-на)</Отчество>
<Состав>n/a</Состав>
<Позиция>Защитник</Позиция>
<Титулы>68</Титулы>
<Вид_спорта>Хокей</Вид_спорта>
<Разряд>2-й разряд</Разряд>
</sportsman>
<sportsman>
<Фамилия>Науменко</Фамилия>
<Имя>Изабелла</Имя>
<Отчество>Валерьянович(-на)</Отчество>
<Состав>Основной</Состав>
<Позиция>Защитник</Позиция>
<Титулы>40</Титулы>
<Вид_спорта>Хокей</Вид_спорта>
<Разряд>КМС</Разряд>
</sportsman>
<sportsman>
<Фамилия>Кузинков(-а)</Фамилия>
<Имя>Игнис</Имя>
<Отчество>Фролович(-на)</Отчество>
<Состав>Запасной</Состав>
<Позиция>Форвард</Позиция>
<Титулы>54</Титулы>
<Вид_спорта>Баскетбол</Вид_спорта>
<Разряд>3-й разряд</Разряд>
</sportsman>
<sportsman>
<Фамилия>Соломин(-а)</Фамилия>
<Имя>Вух</Имя>
<Отчество>Валерьянович(-на)</Отчество>
<Состав>n/a</Состав>
<Позиция>Форвард</Позиция>
<Титулы>40</Титулы>
<Вид_спорта>Футбол</Вид_спорта>
<Разряд>мастер спорта</Разряд>
</sportsman>
<sportsman>
<Фамилия>Кузинков(-а)</Фамилия>
<Имя>Роберт</Имя>
<Отчество>Валерьянович(-на)</Отчество>
<Состав>n/a</Состав>
<Позиция>Форвард</Позиция>
<Титулы>39</Титулы>
<Вид_спорта>Пляж. Футбол</Вид_спорта>
<Разряд>2-й разряд</Разряд>
</sportsman>
<sportsman>
<Фамилия>Палюлин(-а)</Фамилия>
<Имя>Изабелла</Имя>
<Отчество>Валерьянович(-на)</Отчество>
<Состав>Основной</Состав>
<Позиция>Форвард</Позиция>
<Титулы>61</Титулы>
<Вид_спорта>Баскетбол</Вид_спорта>
<Разряд>мастер спорта</Разряд>
</sportsman>
<sportsman>
<Фамилия>Кузинков(-а)</Фамилия>
<Имя>Евдоким</Имя>
<Отчество>Игнатиевич(-на)</Отчество>
<Состав>n/a</Состав>
<Позиция>Защитник</Позиция>
<Титулы>38</Титулы>
<Вид_спорта>Волейбол</Вид_спорта>
<Разряд>3-й разряд</Разряд>
</sportsman>
<sportsman>
<Фамилия>Соломин(-а)</Фамилия>
<Имя>Дина</Имя>
<Отчество>Ипполитович(-на)</Отчество>
<Состав>Основной</Состав>
<Позиция>Защитник</Позиция>
<Титулы>33</Титулы>
<Вид_спорта>Баскетбол</Вид_спорта>
<Разряд>2-й разряд</Разряд>
</sportsman>
<sportsman>
<Фамилия>Соломин(-а)</Фамилия>
<Имя>Уй</Имя>
<Отчество>Валерьянович(-на)</Отчество>
<Состав>n/a</Состав>
<Позиция>Защитник</Позиция>
<Титулы>45</Титулы>
<Вид_спорта>Пляж. Футбол</Вид_спорта>
<Разряд>1-й юношеский</Разряд>
</sportsman>
<sportsman>
<Фамилия>Болокан(-а)</Фамилия>
<Имя>Владимир</Имя>
<Отчество>Валерьянович(-на)</Отчество>
<Состав>n/a</Состав>
<Позиция>Форвард</Позиция>
<Титулы>55</Титулы>
<Вид_спорта>Пляж. Футбол</Вид_спорта>
<Разряд>КМС</Разряд>
</sportsman>
<sportsman>
<Фамилия>Николаев(-а)</Фамилия>
<Имя>Вух</Имя>
<Отчество>Игнатиевич(-на)</Отчество>
<Состав>n/a</Состав>
<Позиция>Форвард</Позиция>
<Титулы>8</Титулы>
<Вид_спорта>Пляж. Футбол</Вид_спорта>
<Разряд>мастер спорта</Разряд>
</sportsman>
<sportsman>
<Фамилия>Болокан(-а)</Фамилия>
<Имя>Уй</Имя>
<Отчество>Фролович(-на)</Отчество>
<Состав>n/a</Состав>
<Позиция>Защитник</Позиция>
<Титулы>76</Титулы>
<Вид_спорта>Волейбол</Вид_спорта>
<Разряд>2-й разряд</Разряд>
</sportsman>
<sportsman>
<Фамилия>Чадов(-а)</Фамилия>
<Имя>Татьяна</Имя>
<Отчество>Феоктистович(-на)</Отчество>
<Состав>n/a</Состав>
<Позиция>Защитник</Позиция>
<Титулы>35</Титулы>
<Вид_спорта>Хокей</Вид_спорта>
<Разряд>1-й юношеский</Разряд>
</sportsman>
<sportsman>
<Фамилия>Гринин(-а)</Фамилия>
<Имя>Евдоким</Имя>
<Отчество>Фролович(-на)</Отчество>
<Состав>Запасной</Состав>
<Позиция>Форвард</Позиция>
<Титулы>24</Титулы>
<Вид_спорта>Хокей</Вид_спорта>
<Разряд>мастер спорта</Разряд>
</sportsman>
<sportsman>
<Фамилия>Болокан(-а)</Фамилия>
<Имя>Измаил</Имя>
<Отчество>Валерьянович(-на)</Отчество>
<Состав>n/a</Состав>
<Позиция>Форвард</Позиция>
<Титулы>52</Титулы>
<Вид_спорта>Пляж. Футбол</Вид_спорта>
<Разряд>КМС</Разряд>
</sportsman>
<sportsman>
<Фамилия>Мишин(-а)</Фамилия>
<Имя>Роберт</Имя>
<Отчество>Ипполитович(-на)</Отчество>
<Состав>Основной</Состав>
<Позиция>Защитник</Позиция>
<Титулы>1</Титулы>
<Вид_спорта>Баскетбол</Вид_спорта>
<Разряд>мастер спорта</Разряд>
</sportsman>
<sportsman>
<Фамилия>Чадов(-а)</Фамилия>
<Имя>Евдоким</Имя>
<Отчество>Валерьянович(-на)</Отчество>
<Состав>Основной</Состав>
<Позиция>Форвард</Позиция>
<Титулы>61</Титулы>
<Вид_спорта>Волейбол</Вид_спорта>
<Разряд>КМС</Разряд>
</sportsman>
<sportsman>
<Фамилия>Науменко</Фамилия>
<Имя>Илья</Имя>
<Отчество>Валерьянович(-на)</Отчество>
<Состав>n/a</Состав>
<Позиция>Форвард</Позиция>
<Титулы>41</Титулы>
<Вид_спорта>Волейбол</Вид_спорта>
<Разряд>1-й юношеский</Разряд>
</sportsman>
<sportsman>
<Фамилия>Палюлин(-а)</Фамилия>
<Имя>Сергей</Имя>
<Отчество>Ипполитович(-на)</Отчество>
<Состав>Основной</Состав>
<Позиция>Форвард</Позиция>
<Титулы>46</Титулы>
<Вид_спорта>Футбол</Вид_спорта>
<Разряд>2-й разряд</Разряд>
</sportsman>
<sportsman>
<Фамилия>Николаев(-а)</Фамилия>
<Имя>Модест</Имя>
<Отчество>Валерьянович(-на)</Отчество>
<Состав>n/a</Состав>
<Позиция>Форвард</Позиция>
<Титулы>45</Титулы>
<Вид_спорта>Волейбол</Вид_спорта>
<Разряд>КМС</Разряд>
</sportsman>
<sportsman>
<Фамилия>Болокан(-а)</Фамилия>
<Имя>Татьяна</Имя>
<Отчество>Фролович(-на)</Отчество>
<Состав>n/a</Состав>
<Позиция>Форвард</Позиция>
<Титулы>2</Титулы>
<Вид_спорта>Футбол</Вид_спорта>
<Разряд>1-й юношеский</Разряд>
</sportsman>
<sportsman>
<Фамилия>Соломин(-а)</Фамилия>
<Имя>Никон</Имя>
<Отчество>Валерьянович(-на)</Отчество>
<Состав>n/a</Состав>
<Позиция>Форвард</Позиция>
<Титулы>42</Титулы>
<Вид_спорта>Волейбол</Вид_спорта>
<Разряд>2-й разряд</Разряд>
</sportsman>
<sportsman>
<Фамилия>Чадов(-а)</Фамилия>
<Имя>Измаил</Имя>
<Отчество>Валерьянович(-на)</Отчество>
<Состав>Запасной</Состав>
<Позиция>Защитник</Позиция>
<Титулы>39</Титулы>
<Вид_спорта>Футбол</Вид_спорта>
<Разряд>мастер спорта</Разряд>
</sportsman>
<sportsman>
<Фамилия>Богоносцев(-а)</Фамилия>
<Имя>Измаил</Имя>
<Отчество>Валерьянович(-на)</Отчество>
<Состав>Основной</Состав>
<Позиция>Защитник</Позиция>
<Титулы>33</Титулы>
<Вид_спорта>Пляж. Футбол</Вид_спорта>
<Разряд>2-й разряд</Разряд>
</sportsman>
<sportsman>
<Фамилия>Болокан(-а)</Фамилия>
<Имя>Матильда</Имя>
<Отчество>Валерьянович(-на)</Отчество>
<Состав>Запасной</Состав>
<Позиция>Защитник</Позиция>
<Титулы>36</Титулы>
<Вид_спорта>Пляж. Футбол</Вид_спорта>
<Разряд>КМС</Разряд>
</sportsman>
<sportsman>
<Фамилия>Соломин(-а)</Фамилия>
<Имя>Игнис</Имя>
<Отчество>Ипатович(-на)</Отчество>
<Состав>n/a</Состав>
<Позиция>Защитник</Позиция>
<Титулы>67</Титулы>
<Вид_спорта>Футбол</Вид_спорта>
<Разряд>2-й разряд</Разряд>
</sportsman>
<sportsman>
<Фамилия>Чадов(-а)</Фамилия>
<Имя>Матильда</Имя>
<Отчество>Валерьянович(-на)</Отчество>
<Состав>Запасной</Состав>
<Позиция>Форвард</Позиция>
<Титулы>41</Титулы>
<Вид_спорта>Баскетбол</Вид_спорта>
<Разряд>2-й разряд</Разряд>
</sportsman>
<sportsman>
<Фамилия>Палюлин(-а)</Фамилия>
<Имя>Изабелла</Имя>
<Отчество>Ипполитович(-на)</Отчество>
<Состав>Основной</Состав>
<Позиция>Форвард</Позиция>
<Титулы>68</Титулы>
<Вид_спорта>Футбол</Вид_спорта>
<Разряд>2-й разряд</Разряд>
</sportsman>
<sportsman>
<Фамилия>Науменко</Фамилия>
<Имя>Модест</Имя>
<Отчество>Ипполитович(-на)</Отчество>
<Состав>n/a</Состав>
<Позиция>Форвард</Позиция>
<Титулы>46</Титулы>
<Вид_спорта>Хокей</Вид_спорта>
<Разряд>КМС</Разряд>
</sportsman>
<sportsman>
<Фамилия>Чадов(-а)</Фамилия>
<Имя>Герман</Имя>
<Отчество>Игнатиевич(-на)</Отчество>
<Состав>Основной</Состав>
<Позиция>Форвард</Позиция>
<Титулы>33</Титулы>
<Вид_спорта>Пляж. Футбол</Вид_спорта>
<Разряд>2-й разряд</Разряд>
</sportsman>
<sportsman>
<Фамилия>Чадов(-а)</Фамилия>
<Имя>Модест</Имя>
<Отчество>Игнатиевич(-на)</Отчество>
<Состав>Основной</Состав>
<Позиция>Защитник</Позиция>
<Титулы>24</Титулы>
<Вид_спорта>Футбол</Вид_спорта>
<Разряд>КМС</Разряд>
</sportsman>
<sportsman>
<Фамилия>Чадов(-а)</Фамилия>
<Имя>Измаил</Имя>
<Отчество>Валерьянович(-на)</Отчество>
<Состав>Основной</Состав>
<Позиция>Защитник</Позиция>
<Титулы>52</Титулы>
<Вид_спорта>Хокей</Вид_спорта>
<Разряд>мастер спорта</Разряд>
</sportsman>
<sportsman>
<Фамилия>Чадов(-а)</Фамилия>
<Имя>Изабелла</Имя>
<Отчество>Ипполитович(-на)</Отчество>
<Состав>n/a</Состав>
<Позиция>Форвард</Позиция>
<Титулы>42</Титулы>
<Вид_спорта>Хокей</Вид_спорта>
<Разряд>мастер спорта</Разряд>
</sportsman>
<sportsman>
<Фамилия>Гринин(-а)</Фамилия>
<Имя>Ольга</Имя>
<Отчество>Игнатиевич(-на)</Отчество>
<Состав>Основной</Состав>
<Позиция>Форвард</Позиция>
<Титулы>2</Титулы>
<Вид_спорта>Баскетбол</Вид_спорта>
<Разряд>3-й разряд</Разряд>
</sportsman>
<sportsman>
<Фамилия>Науменко</Фамилия>
<Имя>Ника</Имя>
<Отчество>Феоктистович(-на)</Отчество>
<Состав>Основной</Состав>
<Позиция>Форвард</Позиция>
<Титулы>31</Титулы>
<Вид_спорта>Волейбол</Вид_спорта>
<Разряд>3-й разряд</Разряд>
</sportsman>
<sportsman>
<Фамилия>Николаев(-а)</Фамилия>
<Имя>Ким</Имя>
<Отчество>Валерьянович(-на)</Отчество>
<Состав>Основной</Состав>
<Позиция>Защитник</Позиция>
<Титулы>4</Титулы>
<Вид_спорта>Футбол</Вид_спорта>
<Разряд>2-й разряд</Разряд>
</sportsman>
<sportsman>
<Фамилия>Болокан(-а)</Фамилия>
<Имя>Модест</Имя>
<Отчество>Моисеевич(-на)</Отчество>
<Состав>Основной</Состав>
<Позиция>Форвард</Позиция>
<Титулы>49</Титулы>
<Вид_спорта>Волейбол</Вид_спорта>
<Разряд>3-й разряд</Разряд>
</sportsman>
<sportsman>
<Фамилия>Мишин(-а)</Фамилия>
<Имя>Никон</Имя>
<Отчество>Валерьянович(-на)</Отчество>
<Состав>n/a</Состав>
<Позиция>Защитник</Позиция>
<Титулы>54</Титулы>
<Вид_спорта>Баскетбол</Вид_спорта>
<Разряд>КМС</Разряд>
</sportsman>
<sportsman>
<Фамилия>Кузинков(-а)</Фамилия>
<Имя>Оксана</Имя>
<Отчество>Моисеевич(-на)</Отчество>
<Состав>Основной</Состав>
<Позиция>Форвард</Позиция>
<Титулы>35</Титулы>
<Вид_спорта>Хокей</Вид_спорта>
<Разряд>КМС</Разряд>
</sportsman>
<sportsman>
<Фамилия>Кузинков(-а)</Фамилия>
<Имя>Оксана</Имя>
<Отчество>Феоктистович(-на)</Отчество>
<Состав>Основной</Состав>
<Позиция>Форвард</Позиция>
<Титулы>12</Титулы>
<Вид_спорта>Баскетбол</Вид_спорта>
<Разряд>мастер спорта</Разряд>
</sportsman>
<sportsman>
<Фамилия>Соломин(-а)</Фамилия>
<Имя>Фридрих</Имя>
<Отчество>Игнатиевич(-на)</Отчество>
<Состав>Запасной</Состав>
<Позиция>Защитник</Позиция>
<Титулы>7</Титулы>
<Вид_спорта>Пляж. Футбол</Вид_спорта>
<Разряд>3-й разряд</Разряд>
</sportsman>
<sportsman>
<Фамилия>Кузинков(-а)</Фамилия>
<Имя>Измаил</Имя>
<Отчество>Валерьянович(-на)</Отчество>
<Состав>n/a</Состав>
<Позиция>Защитник</Позиция>
<Титулы>12</Титулы>
<Вид_спорта>Пляж. Футбол</Вид_спорта>
<Разряд>КМС</Разряд>
</sportsman>
<sportsman>
<Фамилия>Болокан(-а)</Фамилия>
<Имя>Ника</Имя>
<Отчество>Валерьянович(-на)</Отчество>
<Состав>n/a</Состав>
<Позиция>Форвард</Позиция>
<Титулы>11</Титулы>
<Вид_спорта>Хокей</Вид_спорта>
<Разряд>мастер спорта</Разряд>
</sportsman>
<sportsman>
<Фамилия>Соломин(-а)</Фамилия>
<Имя>Эдуард</Имя>
<Отчество>Валерьянович(-на)</Отчество>
<Состав>Запасной</Состав>
<Позиция>Форвард</Позиция>
<Титулы>59</Титулы>
<Вид_спорта>Пляж. Футбол</Вид_спорта>
<Разряд>1-й юношеский</Разряд>
</sportsman>
<sportsman>
<Фамилия>Соломин(-а)</Фамилия>
<Имя>Ника</Имя>
<Отчество>Феоктистович(-на)</Отчество>
<Состав>Основной</Состав>
<Позиция>Форвард</Позиция>
<Титулы>70</Титулы>
<Вид_спорта>Футбол</Вид_спорта>
<Разряд>1-й юношеский</Разряд>
</sportsman>
<sportsman>
<Фамилия>Гринин(-а)</Фамилия>
<Имя>Эдуард</Имя>
<Отчество>Валерьянович(-на)</Отчество>
<Состав>Запасной</Состав>
<Позиция>Форвард</Позиция>
<Титулы>4</Титулы>
<Вид_спорта>Баскетбол</Вид_спорта>
<Разряд>КМС</Разряд>
</sportsman>
<sportsman>
<Фамилия>Науменко</Фамилия>
<Имя>Дина</Имя>
<Отчество>Ипатович(-на)</Отчество>
<Состав>Основной</Состав>
<Позиция>Форвард</Позиция>
<Титулы>47</Титулы>
<Вид_спорта>Хокей</Вид_спорта>
<Разряд>мастер спорта</Разряд>
</sportsman>
<sportsman>
<Фамилия>Чадов(-а)</Фамилия>
<Имя>Илья</Имя>
<Отчество>Валерьянович(-на)</Отчество>
<Состав>Основной</Состав>
<Позиция>Форвард</Позиция>
<Титулы>76</Титулы>
<Вид_спорта>Баскетбол</Вид_спорта>
<Разряд>2-й разряд</Разряд>
</sportsman>
<sportsman>
<Фамилия>Кузинков(-а)</Фамилия>
<Имя>Фридрих</Имя>
<Отчество>Ипполитович(-на)</Отчество>
<Состав>Запасной</Состав>
<Позиция>Форвард</Позиция>
<Титулы>55</Титулы>
<Вид_спорта>Баскетбол</Вид_спорта>
<Разряд>КМС</Разряд>
</sportsman>
<sportsman>
<Фамилия>Болокан(-а)</Фамилия>
<Имя>Ника</Имя>
<Отчество>Моисеевич(-на)</Отчество>
<Состав>Основной</Состав>
<Позиция>Защитник</Позиция>
<Титулы>77</Титулы>
<Вид_спорта>Пляж. Футбол</Вид_спорта>
<Разряд>КМС</Разряд>
</sportsman>
</Sportsmans>
